Cosmic/__init__.py
Cosmic/cosmiclogger.py
CosmicLogger-0.0.1.dist-info/METADATA
CosmicLogger-0.0.1.dist-info/WHEEL
CosmicLogger-0.0.1.dist-info/top_level.txt
CosmicLogger-0.0.1.dist-info/RECORD
