Metadata-Version: 2.1
Name: CosmicLogger
Version: 0.0.1
Summary: Logger
Author: Developer Ravan
Author-email: vivekxd669@gmail.com
Keywords: python,tutorial,CosmicLogger,area,developerravan
Classifier: Development Status :: 1 - Planning
Classifier: Intended Audience :: Developers
Classifier: Programming Language :: Python :: 3
Classifier: Operating System :: Unix
Classifier: Operating System :: MacOS :: MacOS X
Classifier: Operating System :: Microsoft :: Windows
Requires-Dist: colorama
Requires-Dist: datetime
Requires-Dist: logging
